{
  "project_info": {
    "project_number": "885773645181",
    "firebase_url": "https://demofirebase-b0a3e.firebaseio.com",
    "project_id": "demofirebase-b0a3e",
    "storage_bucket": "demofirebase-b0a3e.appspot.com"
  },
  "client": [
    {
      "client_info": {
        "mobilesdk_app_id": "1:885773645181:android:75745c856167012a7c8814",
        "android_client_info": {
          "package_name": "com.amigoapps.vidyantrik"
        }
      },
      "oauth_client": [
        {
          "client_id": "885773645181-9a97fl545r62p0j34ajrdplrv1tq67b2.apps.googleusercontent.com",
          "client_type": 3
        }
      ],
      "api_key": [
        {
          "current_key": "AIzaSyAwP60BmhdsCIEOynvLY1Dfin9GRPDdCFg"
        }
      ],
      "services": {
        "appinvite_service": {
          "other_platform_oauth_client": [
            {
              "client_id": "885773645181-9a97fl545r62p0j34ajrdplrv1tq67b2.apps.googleusercontent.com",
              "client_type": 3
            }
          ]
        }
      }
    }
  ],
  "configuration_version": "1"
}